odoo8_addon_document_page_health_safety_manual-8.0.1.0.0-py2.7-nspkg.pth
odoo_addons/document_page_health_safety_manual/__openerp__.py
odoo_addons/document_page_health_safety_manual/document_page_health_safety_manual.xml
odoo_addons/document_page_health_safety_manual/__init__.py
odoo_addons/document_page_health_safety_manual/README.rst
odoo_addons/document_page_health_safety_manual/migrations/7.0.1.0/post-migration.py
odoo_addons/document_page_health_safety_manual/static/description/icon.png
odoo8_addon_document_page_health_safety_manual-8.0.1.0.0.dist-info/top_level.txt
odoo8_addon_document_page_health_safety_manual-8.0.1.0.0.dist-info/WHEEL
odoo8_addon_document_page_health_safety_manual-8.0.1.0.0.dist-info/RECORD
odoo8_addon_document_page_health_safety_manual-8.0.1.0.0.dist-info/metadata.json
odoo8_addon_document_page_health_safety_manual-8.0.1.0.0.dist-info/DESCRIPTION.rst
odoo8_addon_document_page_health_safety_manual-8.0.1.0.0.dist-info/METADATA
odoo8_addon_document_page_health_safety_manual-8.0.1.0.0.dist-info/namespace_packages.txt
